xrrloader/__init__.py
xrrloader/dataloader/__init__.py
xrrloader/dataloader/exceptions.py
xrrloader/dataloader/fio_loader.py
xrrloader/dataloader/reflectivity_loader.py
xrrloader/dataloader/scans.py
xrrloader/dataloader/spec_loader.py
xrrloader/dataloader/transform.py
xrrloader/footprint/__init__.py
xrrloader/footprint/footprint.py
xrrloader/footprint/normalization.py
xrrloader/p08tools/P08ScanTools.py
xrrloader/p08tools/__init__.py
xrrloader/p08tools/fio_reader.py
xrrloader/parser/__init__.py
xrrloader/parser/fio_parser.py
xrrloader/parser/spec_parser.py
xrrloader-1.1.0.dist-info/LICENSE
xrrloader-1.1.0.dist-info/METADATA
xrrloader-1.1.0.dist-info/WHEEL
xrrloader-1.1.0.dist-info/top_level.txt
xrrloader-1.1.0.dist-info/RECORD
