Metadata-Version: 2.1
Name: xrrloader
Version: 1.1.0
Summary: UNKNOWN
Home-page: UNKNOWN
Author: Alessandro Greco
Author-email: alessandro.greco@uni-tuebingen.de
License: GPL3
Platform: UNKNOWN
Requires-Python: >=3.6
Requires-Dist: setuptools
Requires-Dist: numpy
Requires-Dist: pandas
Requires-Dist: scipy
Requires-Dist: matplotlib
Requires-Dist: fabio
Requires-Dist: h5py
